[
  {
    "id": "1",
    "image": "assets/images/circles.svg",
    "animated_image": null
  },
  {
    "id": "2",
    "image": "assets/images/big_small.svg",
    "animated_image": "assets/images/rabbitWithRocket.svg"
  },
  {
    "id": "3",
    "image": "assets/images/human.svg",
    "animated_image": null
  },
  {
    "id": "4",
    "image": "assets/images/fish.svg",
    "animated_image": "assets/images/rabbit_winking.svg"
  },
  {
    "id": "5",
    "image": "assets/images/fish.svg",
    "animated_image": null
  },
  {
    "id": "6",
    "image": "assets/images/circles.svg",
    "animated_image": "assets/images/rabbitWithRocket.svg"
  },
  {
    "id": "7",
    "image": "assets/images/big_small.svg",
    "animated_image": null
  },
  {
    "id": "8",
    "image": "assets/images/human.svg",
    "animated_image": "assets/images/rabbit_winking.svg"
  },
  {
    "id": "9",
    "image": "assets/images/fish.svg",
    "animated_image": null
  },
  {
    "id": "10",
    "image": "assets/images/fish.svg",
    "animated_image": "assets/images/rabbitWithRocket.svg"
  },
  {
    "id": "11",
    "image": "assets/images/circles.svg",
    "animated_image": null
  },
  {
    "id": "12",
    "image": "assets/images/big_small.svg",
    "animated_image": "assets/images/rabbitWithRocket.svg"
  },
  {
    "id": "13",
    "image": "assets/images/human.svg",
    "animated_image": null
  },
  {
    "id": "14",
    "image": "assets/images/fish.svg",
    "animated_image": "assets/images/rabbit_winking.svg"
  },
  {
    "id": "15",
    "image": "assets/images/fish.svg",
    "animated_image": null
  }
]